{"sections":{"main":{"type":"main-product","blocks":{"0dc99a94-257c-4236-b14a-dfb3c5dc3e9b":{"type":"text","settings":{"text":"The delivery is expected 3 months after the order is received","bg_color":""}},"c2340c73-d5b2-4a26-96bc-9bf992ce6c27":{"type":"text","disabled":true,"settings":{"text":"<strong style=\"color: red;\">Free 100\" Screen Save $1500！<\/strong>","bg_color":""}},"841155ef-ea23-4084-8967-e96c89c112ff":{"type":"shopify:\/\/apps\/rivyo-product-reviews\/blocks\/wc-product-review-badge\/f1860e84-309f-40ca-a2df-188435a622f3","disabled":true,"settings":{}},"d63f7367-caeb-4b08-8ba1-7dce61642e29":{"type":"text","disabled":true,"settings":{"text":"• AWOL Pays your sales tax. Taxes are built into AWOL Visions prices, saving you hundreds of dollars per order.","bg_color":""}},"cd8f2b73-dac0-424c-b564-4456725af17d":{"type":"text","disabled":true,"settings":{"text":"<strong style=\" margin: 0;\">•Free Gifts Included on Flash Sale <\/strong>","bg_color":""}},"629d1a20-0f73-4655-80aa-9d108f6cd18c":{"type":"text","disabled":true,"settings":{"text":"<strong style=\" color:#de2a2a\">•Tax-Inclusive, Save Around  $500 For You <\/strong>\n<p style=\"margin: 0;\">•Better Price and Service in Buy With Prime <\/p>","bg_color":""}},"c73de1a2-8a33-4f57-b9ea-ff87e98d1c4b":{"type":"gift","disabled":true,"settings":{"variants_id":""}},"d160fe17-7768-41ff-9e77-e3a0d3e59854":{"type":"gift","disabled":true,"settings":{"variants_id":""}},"f15bb9ad-3362-438b-86d9-cffdde2f93b2":{"type":"text","disabled":true,"settings":{"text":"Estimated delivery:<br>LTV-3500 Pro: 2 to 6 days<br>Cinematic 150\": 10 to 16 days","bg_color":""}},"variant_picker":{"type":"variant_picker","settings":{"hide_sold_out_variants":false,"selector_mode":"block","color_mode":"color","size_chart_page":""}},"ae32a676-4a00-4bc1-9367-4e6817ea1376":{"type":"code_copy","disabled":true,"settings":{"code":"FEB1000","code_priceinfo":"Save $1000","code_copybtn":"Code Copy"}},"6e9a414a-2565-4432-b6d3-a6347d0eed93":{"type":"inventory","disabled":true,"settings":{"low_inventory_threshold":0}},"quantity_selector":{"type":"quantity_selector","settings":{}},"d41c3a25-e53f-4b05-931f-25e797d24505":{"type":"gift","settings":{"variants_id":""}},"19c654eb-655e-4b17-8e44-9cfac438ee1f":{"type":"gift","disabled":true,"settings":{"variants_id":"40777846194224"}},"buy_buttons":{"type":"buy_buttons","settings":{"show_payment_button":false,"atc_button_background":"#282828","atc_button_text_color":"#ffffff","buy_now_button_background":"#de2a2a","buy_now_button_text_color":"#ffffff"}},"5936983f-6c55-49dd-a321-625c607ea77e":{"type":"description","disabled":true,"settings":{}}},"block_order":["0dc99a94-257c-4236-b14a-dfb3c5dc3e9b","c2340c73-d5b2-4a26-96bc-9bf992ce6c27","841155ef-ea23-4084-8967-e96c89c112ff","d63f7367-caeb-4b08-8ba1-7dce61642e29","cd8f2b73-dac0-424c-b564-4456725af17d","629d1a20-0f73-4655-80aa-9d108f6cd18c","c73de1a2-8a33-4f57-b9ea-ff87e98d1c4b","d160fe17-7768-41ff-9e77-e3a0d3e59854","f15bb9ad-3362-438b-86d9-cffdde2f93b2","variant_picker","ae32a676-4a00-4bc1-9367-4e6817ea1376","6e9a414a-2565-4432-b6d3-a6347d0eed93","quantity_selector","d41c3a25-e53f-4b05-931f-25e797d24505","19c654eb-655e-4b17-8e44-9cfac438ee1f","buy_buttons","5936983f-6c55-49dd-a321-625c607ea77e"],"settings":{"title_font_size":"h4","show_price":true,"show_subTitle":true,"show_vendor":false,"show_sku":false,"show_taxes_included":true,"show_product_rating":false,"show_sticky_add_to_cart":true,"show_share_buttons":false,"help_page":"","enable_video_autoplay":true,"enable_video_looping":false,"enable_image_zoom":true,"show_thumbnails_on_mobile":true,"desktop_thumbnails_position":"bottom","transition_effect":"slide"}},"11e44bbf-e01f-4e6c-8c5a-990b7fa6cd20":{"type":"product-floor-rising-projector-screen","blocks":{"079fd49e-38ef-463d-85be-f8492d4d49f0":{"type":"imageWithTextr","settings":{"isNeedSwiper":false,"swiperType":"none","image_pc":"shopify:\/\/shop_images\/rs1.png","image_mobile":"shopify:\/\/shop_images\/rs1_m.png","headTitle":"<h3 style=\"text-align: center;\"><strong>Maximize your home theater<br>experience with top-level materials<\/strong><\/h3>","headColor":"#ffffff","head_font_size":32,"context_little_title":"","context":"<p style=\"text-align: center\">-AWOL VISION 120\" Cinematic ALR Floor Rising Screen <\/p>","contextColor":"#ffffff","context_font_size":18,"text_position_left":50,"text_position_top":3}},"ec148676-a131-477b-9c25-4bcfc45c70b7":{"type":"imageWithTextr","settings":{"isNeedSwiper":false,"swiperType":"none","image_pc":"shopify:\/\/shop_images\/rs2.png","image_mobile":"shopify:\/\/shop_images\/rs2_m.png","headTitle":"","headColor":"","head_font_size":36,"context_little_title":"","context":"","contextColor":"","context_font_size":22,"text_position_left":10,"text_position_top":10}},"aa978aa8-a502-498c-9b3f-76698f7b55ab":{"type":"imageWithTextr","settings":{"isNeedSwiper":false,"swiperType":"none","image_pc":"shopify:\/\/shop_images\/rs3.png","image_mobile":"shopify:\/\/shop_images\/rs3_m.png","headTitle":"<h3><strong>Projector's partner in sync. <br>Effortless rise and fall<\/strong><\/h3>","headColor":"#ffffff","head_font_size":32,"context_little_title":"","context":"Just connect the USB Synchronized Trigger to your <br>projector's USB port, and watch in awe as the motorized <br>screen rises when you power on the projector and<br>lowers when you power it off.","contextColor":"#ffffff","context_font_size":18,"text_position_left":4,"text_position_top":10}},"9b4f711c-7c68-4aa6-9f43-f986602b6599":{"type":"imageWithTextr","settings":{"isNeedSwiper":false,"swiperType":"none","image_pc":"shopify:\/\/shop_images\/rs4.png","image_mobile":"shopify:\/\/shop_images\/rs4_m.png","headTitle":"<h3>3D stereo surround sound<\/h3>","headColor":"#ffffff","head_font_size":32,"context_little_title":"","context":"0.4mm sound hole is designed with an acoustic <br>transparent feature for a surround sound <br>experience that will give you all the cinematic thrill","contextColor":"#ffffff","context_font_size":18,"text_position_left":52,"text_position_top":60}},"a34dd776-044f-4d25-931b-f3de88880726":{"type":"imageWithTextr","settings":{"isNeedSwiper":false,"swiperType":"none","image_pc":"shopify:\/\/shop_images\/rs5.png","image_mobile":"shopify:\/\/shop_images\/rs5_m.png","headTitle":"<h3>Premiurm HBSI <br>\nALR screen<\/h3>","headColor":"#ffffff","head_font_size":32,"context_little_title":"","context":"material-without any\n<br>contrast sacrifice","contextColor":"#ffffff","context_font_size":18,"text_position_left":4,"text_position_top":16}},"215ecce4-02cb-470f-a32e-7e9d8a36a0ae":{"type":"imageWithTextr","settings":{"isNeedSwiper":false,"swiperType":"none","image_pc":"shopify:\/\/shop_images\/rs6.png","image_mobile":"shopify:\/\/shop_images\/rs6_m.png","headTitle":"<h3 style=\"text-align: center;\">95% Ceiling Ambient Light Rejecting<\/h3>","headColor":"#ffffff","head_font_size":32,"context_little_title":"","context":"","contextColor":"","context_font_size":22,"text_position_left":50,"text_position_top":12}},"b3ea4e49-26d5-4652-b0d8-93ae6637063d":{"type":"imageWithTextr","settings":{"isNeedSwiper":false,"swiperType":"one","image_pc":"shopify:\/\/shop_images\/rs7.png","image_mobile":"shopify:\/\/shop_images\/rs7_m.png","headTitle":"","headColor":"","head_font_size":36,"context_little_title":"","context":"","contextColor":"","context_font_size":22,"text_position_left":10,"text_position_top":10}},"ea87db81-0464-488f-883f-1b9425436d4c":{"type":"imageWithTextr","settings":{"isNeedSwiper":false,"swiperType":"one","image_pc":"shopify:\/\/shop_images\/rs8.png","image_mobile":"shopify:\/\/shop_images\/rs8_m.png","headTitle":"<h3>Elevate your entertainment with a<br>\nscreen that rises from the ground<\/h3>","headColor":"#282828","head_font_size":24,"context_little_title":"","context":"","contextColor":"","context_font_size":22,"text_position_left":4,"text_position_top":20}},"4a3348ad-bd15-4c14-b073-54ce0421b664":{"type":"imageWithTextr","settings":{"isNeedSwiper":false,"swiperType":"one","image_pc":"shopify:\/\/shop_images\/rs9.png","image_mobile":"shopify:\/\/shop_images\/rs9_m.png","headTitle":"<h3>170° wide viewing angle<\/h3>","headColor":"#ffffff","head_font_size":32,"context_little_title":"","context":"","contextColor":"","context_font_size":22,"text_position_left":50,"text_position_top":60}}},"block_order":["079fd49e-38ef-463d-85be-f8492d4d49f0","ec148676-a131-477b-9c25-4bcfc45c70b7","aa978aa8-a502-498c-9b3f-76698f7b55ab","9b4f711c-7c68-4aa6-9f43-f986602b6599","a34dd776-044f-4d25-931b-f3de88880726","215ecce4-02cb-470f-a32e-7e9d8a36a0ae","b3ea4e49-26d5-4652-b0d8-93ae6637063d","ea87db81-0464-488f-883f-1b9425436d4c","4a3348ad-bd15-4c14-b073-54ce0421b664"],"disabled":true,"settings":{}},"1655846607f2692918":{"type":"text-with-icons","blocks":{"1655846607622dba61-1":{"type":"item","settings":{"icon":"picto-return-box","custom_icon_width":50,"title":"30 DAY MONEY BACK GUARANTEE","content":""}},"1655846607622dba61-2":{"type":"item","settings":{"icon":"picto-lock","custom_icon_width":50,"title":"24 MONTH HASSLE-FREE WARRANTY","content":""}},"1655846607622dba61-3":{"type":"item","settings":{"icon":"picto-email","custom_icon_width":50,"title":"LIFETIME CUSTOMER SUPPORT","content":""}},"1655846607622dba61-0":{"type":"item","settings":{"icon":"picto-box","custom_icon_width":50,"title":"Free Shipping","content":""}}},"block_order":["1655846607622dba61-1","1655846607622dba61-2","1655846607622dba61-3","1655846607622dba61-0"],"settings":{"background":"rgba(0,0,0,0)","text_color":"rgba(0,0,0,0)","trust_global":false}},"product-content":{"type":"product-content","blocks":{"description":{"type":"description","settings":{}},"f8ddc6b0-e1be-4b63-a706-35b59ed78fc5":{"type":"trust","disabled":true,"settings":{"icon_1":"picto-customer-support","title_1":"Shipping & Returns","content_1":"<p>Add text about your shipping policy<\/p>","icon_2":"picto-warranty","title_2":"Warranty","content_2":"<p>Add text about your product warranty<\/p>","icon_3":"picto-secure-payment","title_3":"Secure Payment","content_3":"<p>Add text about your payment<\/p>"}}},"block_order":["description","f8ddc6b0-e1be-4b63-a706-35b59ed78fc5"],"settings":{}},"1686562697ba628a94":{"type":"apps","blocks":{"bba8b4da-e521-4001-8bfb-0b5679f4ad6a":{"type":"shopify:\/\/apps\/rivyo-product-reviews\/blocks\/wc-review-section\/f1860e84-309f-40ca-a2df-188435a622f3","settings":{}}},"block_order":["bba8b4da-e521-4001-8bfb-0b5679f4ad6a"],"settings":{"include_horizontal_margins":true,"include_vertical_margins":true}},"product-recommendations":{"type":"product-recommendations","settings":{"subheading":"","title":"You may also like","recommendations_count":4,"products":["ltv3500-march-2023-version-plus-100-120-daylight-alr-screen-bundle","ltv-3500-pro-100-120-motorized-floor-rising-projector-screen","ltv-3500-pro-100-120-motorized-floor-rising-projector-screen"],"background":"rgba(0,0,0,0)","text_color":"rgba(0,0,0,0)"}}},"order":["main","11e44bbf-e01f-4e6c-8c5a-990b7fa6cd20","1655846607f2692918","product-content","1686562697ba628a94","product-recommendations"]}